Workbook

Sheet Instrucciones
B2: Kit Autónomo 2027 — Facturas, gastos e impuestos en una sola hoja
B4: CÓMO USARLO (5 minutos):
B5: 1. Ve a la hoja «Config» y rellena tus datos, el año y tu % de retención de IRPF (15% general, 7% los 3 primeros años).
B6: 2. Cada vez que emitas una factura, añade una fila en «Ingresos». Solo rellenas las celdas amarillas; el resto se calcula solo.
B7: 3. Cada vez que pagues un gasto de la actividad, añade una fila en «Gastos» con su categoría y el % deducible.
B8: 4. En «Trimestres» tienes calculado el resultado orientativo del Modelo 303 (IVA) y del Modelo 130 (IRPF) de cada trimestre.
B9: 5. En «Resumen» ves ingresos, gastos y beneficio mes a mes, con gráfico.
B10: 6. En «Factura» escribe el nº de factura y se genera la factura lista para exportar a PDF (Archivo > Exportar > PDF).
B12: LEYENDA: celdas amarillas = las rellenas tú · celdas grises = fórmulas (no tocar).
B14: PLAZOS AEAT (303 y 130): T1 hasta el 20 de abril · T2 hasta el 20 de julio · T3 hasta el 20 de octubre · T4 hasta el 30 de enero.
B16: AVISO: este kit es una herramienta de organización y cálculo orientativo. No sustituye el asesoramiento de un gestor
B17: o asesor fiscal. Casos especiales (recargo de equivalencia, módulos, operaciones intracomunitarias, prorrata) no están cubiertos.
B19: Funciona en Microsoft Excel, Google Sheets (Archivo > Importar) y LibreOffice Calc.

Sheet Config
A1: Configuración
A3: Nombre / Razón social | B3: Tu Nombre Apellido
A4: NIF | B4: 00000000T
A5: Dirección | B5: Calle Ejemplo 1, 28001 Madrid
A6: Email | B6: tu@email.com
A7: IBAN (para facturas) | B7: ES00 0000 0000 0000 0000 0000
A8: Año fiscal | B8: 2027
A9: % IVA por defecto | B9: 0.21
A10: % retención IRPF en facturas | B10: 0.15
A11: % pago fraccionado Modelo 130 | B11: 0.2
A14: Categorías de gasto
A15: Software y suscripciones
A16: Material de oficina
A17: Equipos informáticos
A18: Suministros (luz, internet, móvil)
A19: Cuota de autónomo (RETA)
A20: Gestoría / asesoría
A21: Publicidad y marketing
A22: Formación
A23: Desplazamientos y dietas
A24: Alquiler local / coworking
A25: Comisiones bancarias
... A27: Otros

Sheet Ingresos
A1: Fecha | B1: Nº factura | C1: Cliente | D1: NIF cliente | E1: Concepto | F1: Base imponible | G1: % IVA | H1: Cuota IVA | I1: % IRPF | J1: Retención IRPF | K1: Total a cobrar | L1: Trimestre | M1: Mes | N1: ¿Cobrada?
A2: =DATE(Config!$B$8,1,15) | B2: 2027-001 | C2: Cliente Ejemplo S.L. | D2: B00000000 | E2: Diseño web (ejemplo, bórrame) | F2: 1000 | G2: =IF(F2="","",Config!$B$9) | H2: =IF(F2="","",ROUND(F2*G2,2)) | I2: =IF(F2="","",Config!$B$10) | J2: =IF(F2="","",ROUND(F2*I2,2)) | K2: =IF(F2="","",F2+H2-J2) | L2: =IF(A2="","",ROUNDUP(MONTH(A2)/3,0)) | M2: =IF(A2="","",MONTH(A2)) | N2: Sí
G3: =IF(F3="","",Config!$B$9) | H3: =IF(F3="","",ROUND(F3*G3,2)) | I3: =IF(F3="","",Config!$B$10) | J3: =IF(F3="","",ROUND(F3*I3,2)) | K3: =IF(F3="","",F3+H3-J3) | L3: =IF(A3="","",ROUNDUP(MONTH(A3)/3,0)) | M3: =IF(A3="","",MONTH(A3))
G4: =IF(F4="","",Config!$B$9) | H4: =IF(F4="","",ROUND(F4*G4,2)) | I4: =IF(F4="","",Config!$B$10) | J4: =IF(F4="","",ROUND(F4*I4,2)) | K4: =IF(F4="","",F4+H4-J4) | L4: =IF(A4="","",ROUNDUP(MONTH(A4)/3,0)) | M4: =IF(A4="","",MONTH(A4))
G5: =IF(F5="","",Config!$B$9) | H5: =IF(F5="","",ROUND(F5*G5,2)) | I5: =IF(F5="","",Config!$B$10) | J5: =IF(F5="","",ROUND(F5*I5,2)) | K5: =IF(F5="","",F5+H5-J5) | L5: =IF(A5="","",ROUNDUP(MONTH(A5)/3,0)) | M5: =IF(A5="","",MONTH(A5))
G6: =IF(F6="","",Config!$B$9) | H6: =IF(F6="","",ROUND(F6*G6,2)) | I6: =IF(F6="","",Config!$B$10) | J6: =IF(F6="","",ROUND(F6*I6,2)) | K6: =IF(F6="","",F6+H6-J6) | L6: =IF(A6="","",ROUNDUP(MONTH(A6)/3,0)) | M6: =IF(A6="","",MONTH(A6))
G7: =IF(F7="","",Config!$B$9) | H7: =IF(F7="","",ROUND(F7*G7,2)) | I7: =IF(F7="","",Config!$B$10) | J7: =IF(F7="","",ROUND(F7*I7,2)) | K7: =IF(F7="","",F7+H7-J7) | L7: =IF(A7="","",ROUNDUP(MONTH(A7)/3,0)) | M7: =IF(A7="","",MONTH(A7))
G8: =IF(F8="","",Config!$B$9) | H8: =IF(F8="","",ROUND(F8*G8,2)) | I8: =IF(F8="","",Config!$B$10) | J8: =IF(F8="","",ROUND(F8*I8,2)) | K8: =IF(F8="","",F8+H8-J8) | L8: =IF(A8="","",ROUNDUP(MONTH(A8)/3,0)) | M8: =IF(A8="","",MONTH(A8))
G9: =IF(F9="","",Config!$B$9) | H9: =IF(F9="","",ROUND(F9*G9,2)) | I9: =IF(F9="","",Config!$B$10) | J9: =IF(F9="","",ROUND(F9*I9,2)) | K9: =IF(F9="","",F9+H9-J9) | L9: =IF(A9="","",ROUNDUP(MONTH(A9)/3,0)) | M9: =IF(A9="","",MONTH(A9))
G10: =IF(F10="","",Config!$B$9) | H10: =IF(F10="","",ROUND(F10*G10,2)) | I10: =IF(F10="","",Config!$B$10) | J10: =IF(F10="","",ROUND(F10*I10,2)) | K10: =IF(F10="","",F10+H10-J10) | L10: =IF(A10="","",ROUNDUP(MONTH(A10)/3,0)) | M10: =IF(A10="","",MONTH(A10))
G11: =IF(F11="","",Config!$B$9) | H11: =IF(F11="","",ROUND(F11*G11,2)) | I11: =IF(F11="","",Config!$B$10) | J11: =IF(F11="","",ROUND(F11*I11,2)) | K11: =IF(F11="","",F11+H11-J11) | L11: =IF(A11="","",ROUNDUP(MONTH(A11)/3,0)) | M11: =IF(A11="","",MONTH(A11))
G12: =IF(F12="","",Config!$B$9) | H12: =IF(F12="","",ROUND(F12*G12,2)) | I12: =IF(F12="","",Config!$B$10) | J12: =IF(F12="","",ROUND(F12*I12,2)) | K12: =IF(F12="","",F12+H12-J12) | L12: =IF(A12="","",ROUNDUP(MONTH(A12)/3,0)) | M12: =IF(A12="","",MONTH(A12))
G13: =IF(F13="","",Config!$B$9) | H13: =IF(F13="","",ROUND(F13*G13,2)) | I13: =IF(F13="","",Config!$B$10) | J13: =IF(F13="","",ROUND(F13*I13,2)) | K13: =IF(F13="","",F13+H13-J13) | L13: =IF(A13="","",ROUNDUP(MONTH(A13)/3,0)) | M13: =IF(A13="","",MONTH(A13))
G14: =IF(F14="","",Config!$B$9) | H14: =IF(F14="","",ROUND(F14*G14,2)) | I14: =IF(F14="","",Config!$B$10) | J14: =IF(F14="","",ROUND(F14*I14,2)) | K14: =IF(F14="","",F14+H14-J14) | L14: =IF(A14="","",ROUNDUP(MONTH(A14)/3,0)) | M14: =IF(A14="","",MONTH(A14))
... G301: =IF(F301="","",Config!$B$9) | H301: =IF(F301="","",ROUND(F301*G301,2)) | I301: =IF(F301="","",Config!$B$10) | J301: =IF(F301="","",ROUND(F301*I301,2)) | K301: =IF(F301="","",F301+H301-J301) | L301: =IF(A301="","",ROUNDUP(MONTH(A301)/3,0)) | M301: =IF(A301="","",MONTH(A301))

Sheet Gastos
A1: Fecha | B1: Proveedor | C1: NIF proveedor | D1: Concepto | E1: Categoría | F1: Base imponible | G1: % IVA | H1: Cuota IVA | I1: Total pagado | J1: % deducible | K1: Base deducible | L1: IVA deducible | M1: Trimestre | N1: Mes
A2: =DATE(Config!$B$8,1,20) | B2: Proveedor Ejemplo | D2: Suscripción software (ejemplo, bórrame) | E2: Software y suscripciones | F2: 50 | G2: 0.21 | H2: =IF(F2="","",ROUND(F2*N(G2),2)) | I2: =IF(F2="","",F2+H2) | J2: 1 | K2: =IF(F2="","",ROUND(F2*IF(J2="",1,J2),2)) | L2: =IF(F2="","",ROUND(H2*IF(J2="",1,J2),2)) | M2: =IF(A2="","",ROUNDUP(MONTH(A2)/3,0)) | N2: =IF(A2="","",MONTH(A2))
A3: =DATE(Config!$B$8,1,31) | B3: Seguridad Social | D3: Cuota autónomo (ejemplo, bórrame) | E3: Cuota de autónomo (RETA) | F3: 80 | G3: 0 | H3: =IF(F3="","",ROUND(F3*N(G3),2)) | I3: =IF(F3="","",F3+H3) | J3: 1 | K3: =IF(F3="","",ROUND(F3*IF(J3="",1,J3),2)) | L3: =IF(F3="","",ROUND(H3*IF(J3="",1,J3),2)) | M3: =IF(A3="","",ROUNDUP(MONTH(A3)/3,0)) | N3: =IF(A3="","",MONTH(A3))
H4: =IF(F4="","",ROUND(F4*N(G4),2)) | I4: =IF(F4="","",F4+H4) | K4: =IF(F4="","",ROUND(F4*IF(J4="",1,J4),2)) | L4: =IF(F4="","",ROUND(H4*IF(J4="",1,J4),2)) | M4: =IF(A4="","",ROUNDUP(MONTH(A4)/3,0)) | N4: =IF(A4="","",MONTH(A4))
H5: =IF(F5="","",ROUND(F5*N(G5),2)) | I5: =IF(F5="","",F5+H5) | K5: =IF(F5="","",ROUND(F5*IF(J5="",1,J5),2)) | L5: =IF(F5="","",ROUND(H5*IF(J5="",1,J5),2)) | M5: =IF(A5="","",ROUNDUP(MONTH(A5)/3,0)) | N5: =IF(A5="","",MONTH(A5))
H6: =IF(F6="","",ROUND(F6*N(G6),2)) | I6: =IF(F6="","",F6+H6) | K6: =IF(F6="","",ROUND(F6*IF(J6="",1,J6),2)) | L6: =IF(F6="","",ROUND(H6*IF(J6="",1,J6),2)) | M6: =IF(A6="","",ROUNDUP(MONTH(A6)/3,0)) | N6: =IF(A6="","",MONTH(A6))
H7: =IF(F7="","",ROUND(F7*N(G7),2)) | I7: =IF(F7="","",F7+H7) | K7: =IF(F7="","",ROUND(F7*IF(J7="",1,J7),2)) | L7: =IF(F7="","",ROUND(H7*IF(J7="",1,J7),2)) | M7: =IF(A7="","",ROUNDUP(MONTH(A7)/3,0)) | N7: =IF(A7="","",MONTH(A7))
H8: =IF(F8="","",ROUND(F8*N(G8),2)) | I8: =IF(F8="","",F8+H8) | K8: =IF(F8="","",ROUND(F8*IF(J8="",1,J8),2)) | L8: =IF(F8="","",ROUND(H8*IF(J8="",1,J8),2)) | M8: =IF(A8="","",ROUNDUP(MONTH(A8)/3,0)) | N8: =IF(A8="","",MONTH(A8))
H9: =IF(F9="","",ROUND(F9*N(G9),2)) | I9: =IF(F9="","",F9+H9) | K9: =IF(F9="","",ROUND(F9*IF(J9="",1,J9),2)) | L9: =IF(F9="","",ROUND(H9*IF(J9="",1,J9),2)) | M9: =IF(A9="","",ROUNDUP(MONTH(A9)/3,0)) | N9: =IF(A9="","",MONTH(A9))
H10: =IF(F10="","",ROUND(F10*N(G10),2)) | I10: =IF(F10="","",F10+H10) | K10: =IF(F10="","",ROUND(F10*IF(J10="",1,J10),2)) | L10: =IF(F10="","",ROUND(H10*IF(J10="",1,J10),2)) | M10: =IF(A10="","",ROUNDUP(MONTH(A10)/3,0)) | N10: =IF(A10="","",MONTH(A10))
H11: =IF(F11="","",ROUND(F11*N(G11),2)) | I11: =IF(F11="","",F11+H11) | K11: =IF(F11="","",ROUND(F11*IF(J11="",1,J11),2)) | L11: =IF(F11="","",ROUND(H11*IF(J11="",1,J11),2)) | M11: =IF(A11="","",ROUNDUP(MONTH(A11)/3,0)) | N11: =IF(A11="","",MONTH(A11))
H12: =IF(F12="","",ROUND(F12*N(G12),2)) | I12: =IF(F12="","",F12+H12) | K12: =IF(F12="","",ROUND(F12*IF(J12="",1,J12),2)) | L12: =IF(F12="","",ROUND(H12*IF(J12="",1,J12),2)) | M12: =IF(A12="","",ROUNDUP(MONTH(A12)/3,0)) | N12: =IF(A12="","",MONTH(A12))
H13: =IF(F13="","",ROUND(F13*N(G13),2)) | I13: =IF(F13="","",F13+H13) | K13: =IF(F13="","",ROUND(F13*IF(J13="",1,J13),2)) | L13: =IF(F13="","",ROUND(H13*IF(J13="",1,J13),2)) | M13: =IF(A13="","",ROUNDUP(MONTH(A13)/3,0)) | N13: =IF(A13="","",MONTH(A13))
H14: =IF(F14="","",ROUND(F14*N(G14),2)) | I14: =IF(F14="","",F14+H14) | K14: =IF(F14="","",ROUND(F14*IF(J14="",1,J14),2)) | L14: =IF(F14="","",ROUND(H14*IF(J14="",1,J14),2)) | M14: =IF(A14="","",ROUNDUP(MONTH(A14)/3,0)) | N14: =IF(A14="","",MONTH(A14))
H15: =IF(F15="","",ROUND(F15*N(G15),2)) | I15: =IF(F15="","",F15+H15) | K15: =IF(F15="","",ROUND(F15*IF(J15="",1,J15),2)) | L15: =IF(F15="","",ROUND(H15*IF(J15="",1,J15),2)) | M15: =IF(A15="","",ROUNDUP(MONTH(A15)/3,0)) | N15: =IF(A15="","",MONTH(A15))
... H301: =IF(F301="","",ROUND(F301*N(G301),2)) | I301: =IF(F301="","",F301+H301) | K301: =IF(F301="","",ROUND(F301*IF(J301="",1,J301),2)) | L301: =IF(F301="","",ROUND(H301*IF(J301="",1,J301),2)) | M301: =IF(A301="","",ROUNDUP(MONTH(A301)/3,0)) | N301: =IF(A301="","",MONTH(A301))

Sheet Trimestres
A1: Impuestos trimestrales (orientativo)
B3: T1 | C3: T2 | D3: T3 | E3: T4 | F3: TOTAL AÑO
A4: MODELO 303 — IVA
A5: IVA repercutido (cobrado en tus facturas) | B5: =SUMIFS(Ingresos!$H$2:$H$301,Ingresos!$L$2:$L$301,1) | C5: =SUMIFS(Ingresos!$H$2:$H$301,Ingresos!$L$2:$L$301,2) | D5: =SUMIFS(Ingresos!$H$2:$H$301,Ingresos!$L$2:$L$301,3) | E5: =SUMIFS(Ingresos!$H$2:$H$301,Ingresos!$L$2:$L$301,4) | F5: =SUM(B5:E5)
A6: IVA soportado deducible (pagado en gastos) | B6: =SUMIFS(Gastos!$L$2:$L$301,Gastos!$M$2:$M$301,1) | C6: =SUMIFS(Gastos!$L$2:$L$301,Gastos!$M$2:$M$301,2) | D6: =SUMIFS(Gastos!$L$2:$L$301,Gastos!$M$2:$M$301,3) | E6: =SUMIFS(Gastos!$L$2:$L$301,Gastos!$M$2:$M$301,4) | F6: =SUM(B6:E6)
A7: Resultado 303 (positivo = a pagar) | B7: =B5-B6 | C7: =C5-C6 | D7: =D5-D6 | E7: =E5-E6 | F7: =SUM(B7:E7)
A9: MODELO 130 — Pago fraccionado IRPF
A10: Ingresos del trimestre (base imponible) | B10: =SUMIFS(Ingresos!$F$2:$F$301,Ingresos!$L$2:$L$301,1) | C10: =SUMIFS(Ingresos!$F$2:$F$301,Ingresos!$L$2:$L$301,2) | D10: =SUMIFS(Ingresos!$F$2:$F$301,Ingresos!$L$2:$L$301,3) | E10: =SUMIFS(Ingresos!$F$2:$F$301,Ingresos!$L$2:$L$301,4) | F10: =SUM(B10:E10)
A11: Gastos deducibles del trimestre | B11: =SUMIFS(Gastos!$K$2:$K$301,Gastos!$M$2:$M$301,1) | C11: =SUMIFS(Gastos!$K$2:$K$301,Gastos!$M$2:$M$301,2) | D11: =SUMIFS(Gastos!$K$2:$K$301,Gastos!$M$2:$M$301,3) | E11: =SUMIFS(Gastos!$K$2:$K$301,Gastos!$M$2:$M$301,4) | F11: =SUM(B11:E11)
A12: Ingresos acumulados en el año | B12: =SUM($B$10:B10) | C12: =SUM($B$10:C10) | D12: =SUM($B$10:D10) | E12: =SUM($B$10:E10)
A13: Gastos acumulados en el año | B13: =SUM($B$11:B11) | C13: =SUM($B$11:C11) | D13: =SUM($B$11:D11) | E13: =SUM($B$11:E11)
A14: Rendimiento neto acumulado | B14: =B12-B13 | C14: =C12-C13 | D14: =D12-D13 | E14: =E12-E13
A15: Pago fraccionado acumulado (20%) | B15: =MAX(0,B14*Config!$B$11) | C15: =MAX(0,C14*Config!$B$11) | D15: =MAX(0,D14*Config!$B$11) | E15: =MAX(0,E14*Config!$B$11)
A16: Retenciones IRPF acumuladas (tus clientes ya pagaron) | B16: =SUMIFS(Ingresos!$J$2:$J$301,Ingresos!$L$2:$L$301,"<="&1) | C16: =SUMIFS(Ingresos!$J$2:$J$301,Ingresos!$L$2:$L$301,"<="&2) | D16: =SUMIFS(Ingresos!$J$2:$J$301,Ingresos!$L$2:$L$301,"<="&3) | E16: =SUMIFS(Ingresos!$J$2:$J$301,Ingresos!$L$2:$L$301,"<="&4)
A17: Pagos 130 de trimestres anteriores | B17: =0 | C17: =SUM($B$18:B18) | D17: =SUM($B$18:C18) | E17: =SUM($B$18:D18)
A18: Resultado 130 (a ingresar) | B18: =MAX(0,B15-B16-B17) | C18: =MAX(0,C15-C16-C17) | D18: =MAX(0,D15-D16-D17) | E18: =MAX(0,E15-E16-E17) | F18: =SUM(B18:E18)
A20: TOTAL estimado a pagar este trimestre (303 + 130) | B20: =MAX(0,B7)+B18 | C20: =MAX(0,C7)+C18 | D20: =MAX(0,D7)+D18 | E20: =MAX(0,E7)+E18 | F20: =SUM(B20:E20)
A21: Beneficio neto del trimestre (antes de IRPF anual) | B21: =B10-B11 | C21: =C10-C11 | D21: =D10-D11 | E21: =E10-E11 | F21: =SUM(B21:E21)
A23: Consejo: aparta cada mes el IVA cobrado y un 20% del beneficio en una cuenta separada. Si el 303 sale negativo puedes compensarlo en trimestres siguientes (o pedir devolución en el T4).

Sheet Resumen
A1: Resumen mensual
A3: Mes | B3: Ingresos (base) | C3: Gastos deducibles | D3: Beneficio | E3: Pendiente de cobro
A4: Enero | B4: =SUMIFS(Ingresos!$F$2:$F$301,Ingresos!$M$2:$M$301,1) | C4: =SUMIFS(Gastos!$K$2:$K$301,Gastos!$N$2:$N$301,1) | D4: =B4-C4 | E4: =SUMIFS(Ingresos!$K$2:$K$301,Ingresos!$M$2:$M$301,1,Ingresos!$N$2:$N$301,"No")
A5: Febrero | B5: =SUMIFS(Ingresos!$F$2:$F$301,Ingresos!$M$2:$M$301,2) | C5: =SUMIFS(Gastos!$K$2:$K$301,Gastos!$N$2:$N$301,2) | D5: =B5-C5 | E5: =SUMIFS(Ingresos!$K$2:$K$301,Ingresos!$M$2:$M$301,2,Ingresos!$N$2:$N$301,"No")
A6: Marzo | B6: =SUMIFS(Ingresos!$F$2:$F$301,Ingresos!$M$2:$M$301,3) | C6: =SUMIFS(Gastos!$K$2:$K$301,Gastos!$N$2:$N$301,3) | D6: =B6-C6 | E6: =SUMIFS(Ingresos!$K$2:$K$301,Ingresos!$M$2:$M$301,3,Ingresos!$N$2:$N$301,"No")
A7: Abril | B7: =SUMIFS(Ingresos!$F$2:$F$301,Ingresos!$M$2:$M$301,4) | C7: =SUMIFS(Gastos!$K$2:$K$301,Gastos!$N$2:$N$301,4) | D7: =B7-C7 | E7: =SUMIFS(Ingresos!$K$2:$K$301,Ingresos!$M$2:$M$301,4,Ingresos!$N$2:$N$301,"No")
A8: Mayo | B8: =SUMIFS(Ingresos!$F$2:$F$301,Ingresos!$M$2:$M$301,5) | C8: =SUMIFS(Gastos!$K$2:$K$301,Gastos!$N$2:$N$301,5) | D8: =B8-C8 | E8: =SUMIFS(Ingresos!$K$2:$K$301,Ingresos!$M$2:$M$301,5,Ingresos!$N$2:$N$301,"No")
A9: Junio | B9: =SUMIFS(Ingresos!$F$2:$F$301,Ingresos!$M$2:$M$301,6) | C9: =SUMIFS(Gastos!$K$2:$K$301,Gastos!$N$2:$N$301,6) | D9: =B9-C9 | E9: =SUMIFS(Ingresos!$K$2:$K$301,Ingresos!$M$2:$M$301,6,Ingresos!$N$2:$N$301,"No")
A10: Julio | B10: =SUMIFS(Ingresos!$F$2:$F$301,Ingresos!$M$2:$M$301,7) | C10: =SUMIFS(Gastos!$K$2:$K$301,Gastos!$N$2:$N$301,7) | D10: =B10-C10 | E10: =SUMIFS(Ingresos!$K$2:$K$301,Ingresos!$M$2:$M$301,7,Ingresos!$N$2:$N$301,"No")
A11: Agosto | B11: =SUMIFS(Ingresos!$F$2:$F$301,Ingresos!$M$2:$M$301,8) | C11: =SUMIFS(Gastos!$K$2:$K$301,Gastos!$N$2:$N$301,8) | D11: =B11-C11 | E11: =SUMIFS(Ingresos!$K$2:$K$301,Ingresos!$M$2:$M$301,8,Ingresos!$N$2:$N$301,"No")
A12: Septiembre | B12: =SUMIFS(Ingresos!$F$2:$F$301,Ingresos!$M$2:$M$301,9) | C12: =SUMIFS(Gastos!$K$2:$K$301,Gastos!$N$2:$N$301,9) | D12: =B12-C12 | E12: =SUMIFS(Ingresos!$K$2:$K$301,Ingresos!$M$2:$M$301,9,Ingresos!$N$2:$N$301,"No")
A13: Octubre | B13: =SUMIFS(Ingresos!$F$2:$F$301,Ingresos!$M$2:$M$301,10) | C13: =SUMIFS(Gastos!$K$2:$K$301,Gastos!$N$2:$N$301,10) | D13: =B13-C13 | E13: =SUMIFS(Ingresos!$K$2:$K$301,Ingresos!$M$2:$M$301,10,Ingresos!$N$2:$N$301,"No")
A14: Noviembre | B14: =SUMIFS(Ingresos!$F$2:$F$301,Ingresos!$M$2:$M$301,11) | C14: =SUMIFS(Gastos!$K$2:$K$301,Gastos!$N$2:$N$301,11) | D14: =B14-C14 | E14: =SUMIFS(Ingresos!$K$2:$K$301,Ingresos!$M$2:$M$301,11,Ingresos!$N$2:$N$301,"No")
A15: Diciembre | B15: =SUMIFS(Ingresos!$F$2:$F$301,Ingresos!$M$2:$M$301,12) | C15: =SUMIFS(Gastos!$K$2:$K$301,Gastos!$N$2:$N$301,12) | D15: =B15-C15 | E15: =SUMIFS(Ingresos!$K$2:$K$301,Ingresos!$M$2:$M$301,12,Ingresos!$N$2:$N$301,"No")
A16: TOTAL | B16: =SUM(B4:B15) | C16: =SUM(C4:C15) | D16: =SUM(D4:D15) | E16: =SUM(E4:E15)
A18: Margen de beneficio | B18: =IF(B16=0,0,D16/B16)
A19: Impuestos trimestrales estimados | B19: =Trimestres!F20
A20: Nº de facturas emitidas | B20: =COUNTA(Ingresos!$B$2:$B$301)

Sheet Factura
B2: FACTURA | D2: Nº factura → | E2: 2027-001
B4: =Config!B3 | D4: Fecha: | E4: =IFERROR(INDEX(Ingresos!$A$2:$A$301,MATCH($E$2,Ingresos!$B$2:$B$301,0)),"")
B5: ="NIF: "&Config!B4
B6: =Config!B5
B7: =Config!B6
B9: FACTURAR A:
B10: =IFERROR(INDEX(Ingresos!$C$2:$C$301,MATCH($E$2,Ingresos!$B$2:$B$301,0)),"")
B11: =IFERROR("NIF: "&INDEX(Ingresos!$D$2:$D$301,MATCH($E$2,Ingresos!$B$2:$B$301,0)),"")
B13: Concepto | E13: Importe
B14: =IFERROR(INDEX(Ingresos!$E$2:$E$301,MATCH($E$2,Ingresos!$B$2:$B$301,0)),"") | E14: =IFERROR(INDEX(Ingresos!$F$2:$F$301,MATCH($E$2,Ingresos!$B$2:$B$301,0)),"")
D16: Base imponible | E16: =IFERROR(INDEX(Ingresos!$F$2:$F$301,MATCH($E$2,Ingresos!$B$2:$B$301,0)),"")
D17: =IFERROR("IVA ("&TEXT(INDEX(Ingresos!$G$2:$G$301,MATCH($E$2,Ingresos!$B$2:$B$301,0)),"0%")&")","IVA") | E17: =IFERROR(INDEX(Ingresos!$H$2:$H$301,MATCH($E$2,Ingresos!$B$2:$B$301,0)),"")
D18: =IFERROR("Retención IRPF (-"&TEXT(INDEX(Ingresos!$I$2:$I$301,MATCH($E$2,Ingresos!$B$2:$B$301,0)),"0%")&")","IRPF") | E18: =IFERROR(-INDEX(Ingresos!$J$2:$J$301,MATCH($E$2,Ingresos!$B$2:$B$301,0)),"")
D19: TOTAL | E19: =IFERROR(INDEX(Ingresos!$K$2:$K$301,MATCH($E$2,Ingresos!$B$2:$B$301,0)),"")
B22: ="Forma de pago: transferencia a "&Config!B7
B23: Gracias por tu confianza.
